{
  "achievements": [
    {
      "id": "hotspot:welcome",
      "title": "Nice to Meet You",
      "description": "Talked to James.",
      "icon": "👋"
    },
    {
      "id": "hotspot:contact",
      "title": "Get in Touch",
      "description": "Found the contact info.",
      "icon": "✉️"
    },
    {
      "id": "hotspot:monkeyboy",
      "title": "Monkey Business",
      "description": "Met the old wizard.",
      "icon": "🐵"
    },
    {
      "id": "hotspot:games",
      "title": "Arcade Visit",
      "description": "Opened the mini games desktop.",
      "icon": "🕹️"
    },
    {
      "id": "demo:lists-add-item",
      "title": "List Maker",
      "description": "Added an item to a to-do list.",
      "icon": "📝"
    },
    {
      "id": "demo:nws-subscribe",
      "title": "Weather Watch",
      "description": "Subscribed to NWS alerts for a location.",
      "icon": "🌩️"
    },
    {
      "id": "hotspot:book-recommender",
      "title": "Bookworm",
      "description": "Visited the book recommender project.",
      "icon": "📚"
    },
    {
      "id": "demo:snake-score-25",
      "title": "Snake Charmer",
      "description": "Scored over 25 in Snake.",
      "icon": "🐍"
    },
    {
      "id": "demo:blackjack-sweep",
      "title": "Card Shark",
      "description": "Enable all 5 hands (3 on mobile), then win every hand in one round.",
      "icon": "🃏"
    },
    {
      "id": "demo:pong-win",
      "title": "Pong Pro",
      "description": "Beat the CPU in Pong on any difficulty.",
      "icon": "🏓"
    },
    {
      "id": "demo:hangman-win",
      "title": "Word Smith",
      "description": "Guessed a Hangman word correctly.",
      "icon": "🔤"
    },
    {
      "id": "map:house-interior",
      "title": "Step Inside",
      "description": "Entered the house.",
      "icon": "🏠"
    },
    {
      "id": "completionist",
      "title": "Completionist",
      "description": "Unlocked every achievement.",
      "icon": "💎",
      "hidden": true
    }
  ]
}
